emmett55/__init__.py
emmett55/__version__.py
emmett55/app.py
emmett55/cache.py
emmett55/cli.py
emmett55/ctx.py
emmett55/datastructures.py
emmett55/extensions.py
emmett55/html.py
emmett55/http.py
emmett55/locals.py
emmett55/parsers.py
emmett55/pipeline.py
emmett55/serializers.py
emmett55/sessions.py
emmett55/templating.py
emmett55/testing.py
emmett55/utils.py
emmett55/routing/__init__.py
emmett55/routing/router.py
emmett55/routing/urls.py
emmett55/tools/__init__.py
emmett55/tools/decorators.py
emmett55/tools/pipes.py
emmett55-1.2.0.dist-info/METADATA
emmett55-1.2.0.dist-info/WHEEL
emmett55-1.2.0.dist-info/entry_points.txt
emmett55-1.2.0.dist-info/licenses/LICENSE
emmett55-1.2.0.dist-info/RECORD
