Metadata-Version: 2.4
Name: emmett55
Version: 1.2.0
Summary: The micro web framework for inventors
Project-URL: Homepage, https://github.com/emmett-framework/emmett55
Project-URL: Documentation, https://emmett.sh/docs
Project-URL: Funding, https://github.com/sponsors/gi0baro
Project-URL: Source, https://github.com/emmett-framework/emmett55
Project-URL: Issues, https://github.com/emmett-framework/emmett55/issues
Author-email: Giovanni Barillari <g@baro.dev>
License-Expression: BSD-3-Clause
License-File: LICENSE
Keywords: asyncio,web
Classifier: Development Status :: 5 - Production/Stable
Classifier: Environment :: Web Environment
Classifier: Framework :: AsyncIO
Classifier: Intended Audience :: Developers
Classifier: License :: OSI Approved :: BSD License
Classifier: Operating System :: OS Independent
Classifier: Programming Language :: Python :: 3
Classifier: Programming Language :: Python :: 3.9
Classifier: Programming Language :: Python :: 3.10
Classifier: Programming Language :: Python :: 3.11
Classifier: Programming Language :: Python :: 3.12
Classifier: Programming Language :: Python :: 3.13
Classifier: Topic :: Internet :: WWW/HTTP :: Dynamic Content
Classifier: Topic :: Software Development :: Libraries :: Python Modules
Requires-Python: >=3.9
Requires-Dist: click>=6.0
Requires-Dist: emmett-core[granian,reload]~=1.3.0
Provides-Extra: orjson
Requires-Dist: orjson~=3.10; extra == 'orjson'
Provides-Extra: rloop
Requires-Dist: rloop~=0.1; (sys_platform != 'win32') and extra == 'rloop'
Provides-Extra: uvloop
Requires-Dist: uvloop>=0.18.0; (sys_platform != 'win32' and platform_python_implementation == 'CPython') and extra == 'uvloop'
